it_status/__init__.py
it_status/status.py
it_status-0.0.9.dist-info/LICENSE
it_status-0.0.9.dist-info/METADATA
it_status-0.0.9.dist-info/WHEEL
it_status-0.0.9.dist-info/top_level.txt
it_status-0.0.9.dist-info/RECORD
