Metadata-Version: 2.1
Name: it-status
Version: 0.0.9
Summary: This package can be used to the MSK IT Status Dashboard
Home-page: UNKNOWN
Author: Julie Perilla Garcia
Author-email: garciaj4@mskcc.org
License: UNKNOWN
Platform: UNKNOWN
Classifier: Programming Language :: Python :: 3
Classifier: License :: OSI Approved :: MIT License
Classifier: Operating System :: OS Independent
Requires-Python: >=3.6
License-File: LICENSE
Requires-Dist: requests
